avijit1996iiti_basic_calculator/__init__.py
avijit1996iiti_basic_calculator/addition.py
avijit1996iiti_basic_calculator/calculator.py
avijit1996iiti_basic_calculator/division.py
avijit1996iiti_basic_calculator/multiplication.py
avijit1996iiti_basic_calculator/substraction.py
avijit1996iiti_basic_calculator-0.0.3.dist-info/LICENSE.txt
avijit1996iiti_basic_calculator-0.0.3.dist-info/METADATA
avijit1996iiti_basic_calculator-0.0.3.dist-info/WHEEL
avijit1996iiti_basic_calculator-0.0.3.dist-info/top_level.txt
avijit1996iiti_basic_calculator-0.0.3.dist-info/RECORD
