Metadata-Version: 2.1
Name: avijit1996iiti-basic-calculator
Version: 0.0.3
Summary: A very basic calculator
Home-page: UNKNOWN
Author: Avijit Bhattacharjee
Author-email: avijit.bhattacharjee1996@gmail.com
License: MIT
Keywords: calculator
Platform: UNKNOWN
Classifier: Development Status :: 5 - Production/Stable
Classifier: Intended Audience :: Education
Classifier: Operating System :: OS Independent
Classifier: License :: OSI Approved :: MIT License
Classifier: Programming Language :: Python :: 3
